[
        {    
            "name":"角色",
            "children":[
                {
                    "name":"独立的创作者",
                    "value":9     
                },
                {
                    "name":"团队的成员",
                    "value":6     
                },
                {
                    "name":"合作式项目的策划者",
                    "value":5     
                },
                {
                    "name":"其他",
                    "value":1     
                }
            ]
        },
        {    
            "name":"接触途径",
            "children":[
                {
                    "name":"艺术圈内有名",
                    "value":4     
                },
                {
                    "name":"Newsletter或其他订阅的Open Call",
                    "value":0    
                },
                {
                    "name":"内部推荐或提名",
                    "value":7    
                },
                {
                    "name":"其他",
                    "value":2     
                }
            ]
        },
        {    
            "name":"申请材料",
            "children":[
                {
                    "name":"文字方案",
                    "value":12    
                },
                {
                    "name":"模型和草图",
                    "value":9     
                },
                {
                    "name":"预算表",
                    "value":6     
                },
                {
                    "name":"技术需求",
                    "value":9     
                },
                {
                    "name":"时间安排",
                    "value":9     
                },
                {
                    "name":"其他",
                    "value":2     
                }
            ]
        },
        {    
            "name":"项目时长",
            "children":[
                {
                    "name":"1个月以内",
                    "value":0     
                },
                {
                    "name":"1-3个月",
                    "value":1     
                },
                {
                    "name":"3-5个月",
                    "value":4     
                },
                {
                    "name":"半年或以上",
                    "value":8     
                }
            ]
        },
        {    
            "name":"机构的支持",
            "children":[
                {
                    "name":"资金",
                    "value":9     
                },
                {
                    "name":"项目指导（tutorial, critique等）",
                    "value":7     
                },
                {
                    "name":"项目商业孵化（和公司对接，路演等）",
                    "value":4     
                },
                {
                    "name":"项目圈内推广（对接策展人，机构，媒体资源）",
                    "value":10     
                },
                {
                    "name":"新技术应用（专门的技术开发团队，来自科技公司的技术demo等）",
                    "value":5     
                },
                {
                    "name":"出版等学术资源",
                    "value":4     
                }
            ]
        }
]
